module/__init__.py
module/ascc.py
asac-0.1.dist-info/METADATA
asac-0.1.dist-info/WHEEL
asac-0.1.dist-info/top_level.txt
asac-0.1.dist-info/RECORD
